{"moduleDefinition":{"range":[5,1,5,52],"value":{"type":"normal","normal":{"moduleName":{"range":[5,8,5,38],"value":["Api","Enum","Patient_update_column"]},"exposingList":{"range":[5,39,5,52],"value":{"type":"all","all":[5,49,5,51]}}}}},"imports":[{"range":[7,1,7,48],"value":{"moduleName":{"range":[7,8,7,19],"value":["Json","Decode"]},"moduleAlias":{"range":[7,23,7,29],"value":["Decode"]},"exposingList":{"range":[7,30,7,48],"value":{"type":"explicit","explicit":[{"range":[7,40,7,47],"value":{"type":"typeOrAlias","typeOrAlias":{"name":"Decoder"}}}]}}}}],"declarations":[{"range":[25,1,36,12],"value":{"type":"typedecl","typedecl":{"documentation":null,"name":{"range":[25,6,25,27],"value":"Patient_update_column"},"generics":[],"constructors":[{"range":[26,7,26,18],"value":{"name":{"range":[26,7,26,18],"value":"Code_postal"},"arguments":[]}},{"range":[27,7,27,24],"value":{"name":{"range":[27,7,27,24],"value":"Date_de_naissance"},"arguments":[]}},{"range":[28,7,28,12],"value":{"name":{"range":[28,7,28,12],"value":"Genre"},"arguments":[]}},{"range":[29,7,29,17],"value":{"name":{"range":[29,7,29,17],"value":"Id_patient"},"arguments":[]}},{"range":[30,7,30,26],"value":{"name":{"range":[30,7,30,26],"value":"Moyen_de_decouverte"},"arguments":[]}},{"range":[31,7,31,10],"value":{"name":{"range":[31,7,31,10],"value":"Nom"},"arguments":[]}},{"range":[32,7,32,17],"value":{"name":{"range":[32,7,32,17],"value":"Numero_rue"},"arguments":[]}},{"range":[33,7,33,11],"value":{"name":{"range":[33,7,33,11],"value":"Pays"},"arguments":[]}},{"range":[34,7,34,13],"value":{"name":{"range":[34,7,34,13],"value":"Prenom"},"arguments":[]}},{"range":[35,7,35,10],"value":{"name":{"range":[35,7,35,10],"value":"Rue"},"arguments":[]}},{"range":[36,7,36,12],"value":{"name":{"range":[36,7,36,12],"value":"Ville"},"arguments":[]}}]}}},{"range":[39,1,41,122],"value":{"type":"function","function":{"documentation":null,"signature":{"range":[39,1,39,34],"value":{"name":{"range":[39,1,39,5],"value":"list"},"typeAnnotation":{"range":[39,8,39,34],"value":{"type":"typed","typed":{"moduleNameAndName":{"range":[39,8,39,12],"value":{"moduleName":[],"name":"List"}},"args":[{"range":[39,13,39,34],"value":{"type":"typed","typed":{"moduleNameAndName":{"range":[39,13,39,34],"value":{"moduleName":[],"name":"Patient_update_column"}},"args":[]}}}]}}}}},"declaration":{"range":[40,1,41,122],"value":{"name":{"range":[40,1,40,5],"value":"list"},"arguments":[],"expression":{"range":[41,5,41,122],"value":{"type":"list","list":[{"range":[41,7,41,18],"value":{"type":"functionOrValue","functionOrValue":{"moduleName":[],"name":"Code_postal"}}},{"range":[41,20,41,37],"value":{"type":"functionOrValue","functionOrValue":{"moduleName":[],"name":"Date_de_naissance"}}},{"range":[41,39,41,44],"value":{"type":"functionOrValue","functionOrValue":{"moduleName":[],"name":"Genre"}}},{"range":[41,46,41,56],"value":{"type":"functionOrValue","functionOrValue":{"moduleName":[],"name":"Id_patient"}}},{"range":[41,58,41,77],"value":{"type":"functionOrValue","functionOrValue":{"moduleName":[],"name":"Moyen_de_decouverte"}}},{"range":[41,79,41,82],"value":{"type":"functionOrValue","functionOrValue":{"moduleName":[],"name":"Nom"}}},{"range":[41,84,41,94],"value":{"type":"functionOrValue","functionOrValue":{"moduleName":[],"name":"Numero_rue"}}},{"range":[41,96,41,100],"value":{"type":"functionOrValue","functionOrValue":{"moduleName":[],"name":"Pays"}}},{"range":[41,102,41,108],"value":{"type":"functionOrValue","functionOrValue":{"moduleName":[],"name":"Prenom"}}},{"range":[41,110,41,113],"value":{"type":"functionOrValue","functionOrValue":{"moduleName":[],"name":"Rue"}}},{"range":[41,115,41,120],"value":{"type":"functionOrValue","functionOrValue":{"moduleName":[],"name":"Ville"}}}]}}}}}}},{"range":[44,1,85,14],"value":{"type":"function","function":{"documentation":null,"signature":{"range":[44,1,44,40],"value":{"name":{"range":[44,1,44,8],"value":"decoder"},"typeAnnotation":{"range":[44,11,44,40],"value":{"type":"typed","typed":{"moduleNameAndName":{"range":[44,11,44,18],"value":{"moduleName":[],"name":"Decoder"}},"args":[{"range":[44,19,44,40],"value":{"type":"typed","typed":{"moduleNameAndName":{"range":[44,19,44,40],"value":{"moduleName":[],"name":"Patient_update_column"}},"args":[]}}}]}}}}},"declaration":{"range":[45,1,85,14],"value":{"name":{"range":[45,1,45,8],"value":"decoder"},"arguments":[],"expression":{"range":[46,5,85,14],"value":{"type":"application","application":[{"range":[46,5,46,18],"value":{"type":"functionOrValue","functionOrValue":{"moduleName":["Decode"],"name":"string"}}},{"range":[47,9,47,11],"value":{"type":"operator","operator":"|>"}},{"range":[47,12,47,26],"value":{"type":"functionOrValue","functionOrValue":{"moduleName":["Decode"],"name":"andThen"}}},{"range":[48,13,85,14],"value":{"type":"parenthesized","parenthesized":{"range":[48,14,85,13],"value":{"type":"lambda","lambda":{"patterns":[{"range":[48,15,48,21],"value":{"type":"var","var":{"value":"string"}}}],"expression":{"range":[49,17,84,143],"value":{"type":"case","case":{"cases":[{"pattern":{"range":[50,21,50,34],"value":{"type":"string","string":{"value":"code_postal"}}},"expression":{"range":[51,25,51,51],"value":{"type":"application","application":[{"range":[51,25,51,39],"value":{"type":"functionOrValue","functionOrValue":{"moduleName":["Decode"],"name":"succeed"}}},{"range":[51,40,51,51],"value":{"type":"functionOrValue","functionOrValue":{"moduleName":[],"name":"Code_postal"}}}]}}},{"pattern":{"range":[53,21,53,40],"value":{"type":"string","string":{"value":"date_de_naissance"}}},"expression":{"range":[54,25,54,57],"value":{"type":"application","application":[{"range":[54,25,54,39],"value":{"type":"functionOrValue","functionOrValue":{"moduleName":["Decode"],"name":"succeed"}}},{"range":[54,40,54,57],"value":{"type":"functionOrValue","functionOrValue":{"moduleName":[],"name":"Date_de_naissance"}}}]}}},{"pattern":{"range":[56,21,56,28],"value":{"type":"string","string":{"value":"genre"}}},"expression":{"range":[57,25,57,45],"value":{"type":"application","application":[{"range":[57,25,57,39],"value":{"type":"functionOrValue","functionOrValue":{"moduleName":["Decode"],"name":"succeed"}}},{"range":[57,40,57,45],"value":{"type":"functionOrValue","functionOrValue":{"moduleName":[],"name":"Genre"}}}]}}},{"pattern":{"range":[59,21,59,33],"value":{"type":"string","string":{"value":"id_patient"}}},"expression":{"range":[60,25,60,50],"value":{"type":"application","application":[{"range":[60,25,60,39],"value":{"type":"functionOrValue","functionOrValue":{"moduleName":["Decode"],"name":"succeed"}}},{"range":[60,40,60,50],"value":{"type":"functionOrValue","functionOrValue":{"moduleName":[],"name":"Id_patient"}}}]}}},{"pattern":{"range":[62,21,62,42],"value":{"type":"string","string":{"value":"moyen_de_decouverte"}}},"expression":{"range":[63,25,63,59],"value":{"type":"application","application":[{"range":[63,25,63,39],"value":{"type":"functionOrValue","functionOrValue":{"moduleName":["Decode"],"name":"succeed"}}},{"range":[63,40,63,59],"value":{"type":"functionOrValue","functionOrValue":{"moduleName":[],"name":"Moyen_de_decouverte"}}}]}}},{"pattern":{"range":[65,21,65,26],"value":{"type":"string","string":{"value":"nom"}}},"expression":{"range":[66,25,66,43],"value":{"type":"application","application":[{"range":[66,25,66,39],"value":{"type":"functionOrValue","functionOrValue":{"moduleName":["Decode"],"name":"succeed"}}},{"range":[66,40,66,43],"value":{"type":"functionOrValue","functionOrValue":{"moduleName":[],"name":"Nom"}}}]}}},{"pattern":{"range":[68,21,68,33],"value":{"type":"string","string":{"value":"numero_rue"}}},"expression":{"range":[69,25,69,50],"value":{"type":"application","application":[{"range":[69,25,69,39],"value":{"type":"functionOrValue","functionOrValue":{"moduleName":["Decode"],"name":"succeed"}}},{"range":[69,40,69,50],"value":{"type":"functionOrValue","functionOrValue":{"moduleName":[],"name":"Numero_rue"}}}]}}},{"pattern":{"range":[71,21,71,27],"value":{"type":"string","string":{"value":"pays"}}},"expression":{"range":[72,25,72,44],"value":{"type":"application","application":[{"range":[72,25,72,39],"value":{"type":"functionOrValue","functionOrValue":{"moduleName":["Decode"],"name":"succeed"}}},{"range":[72,40,72,44],"value":{"type":"functionOrValue","functionOrValue":{"moduleName":[],"name":"Pays"}}}]}}},{"pattern":{"range":[74,21,74,29],"value":{"type":"string","string":{"value":"prenom"}}},"expression":{"range":[75,25,75,46],"value":{"type":"application","application":[{"range":[75,25,75,39],"value":{"type":"functionOrValue","functionOrValue":{"moduleName":["Decode"],"name":"succeed"}}},{"range":[75,40,75,46],"value":{"type":"functionOrValue","functionOrValue":{"moduleName":[],"name":"Prenom"}}}]}}},{"pattern":{"range":[77,21,77,26],"value":{"type":"string","string":{"value":"rue"}}},"expression":{"range":[78,25,78,43],"value":{"type":"application","application":[{"range":[78,25,78,39],"value":{"type":"functionOrValue","functionOrValue":{"moduleName":["Decode"],"name":"succeed"}}},{"range":[78,40,78,43],"value":{"type":"functionOrValue","functionOrValue":{"moduleName":[],"name":"Rue"}}}]}}},{"pattern":{"range":[80,21,80,28],"value":{"type":"string","string":{"value":"ville"}}},"expression":{"range":[81,25,81,45],"value":{"type":"application","application":[{"range":[81,25,81,39],"value":{"type":"functionOrValue","functionOrValue":{"moduleName":["Decode"],"name":"succeed"}}},{"range":[81,40,81,45],"value":{"type":"functionOrValue","functionOrValue":{"moduleName":[],"name":"Ville"}}}]}}},{"pattern":{"range":[83,21,83,22],"value":{"type":"all","all":{}}},"expression":{"range":[84,25,84,143],"value":{"type":"application","application":[{"range":[84,25,84,36],"value":{"type":"functionOrValue","functionOrValue":{"moduleName":["Decode"],"name":"fail"}}},{"range":[84,37,84,143],"value":{"type":"parenthesized","parenthesized":{"range":[84,38,84,142],"value":{"type":"application","application":[{"range":[84,38,84,76],"value":{"type":"literal","literal":"Invalid Patient_update_column type, "}},{"range":[84,77,84,79],"value":{"type":"operator","operator":"++"}},{"range":[84,80,84,86],"value":{"type":"functionOrValue","functionOrValue":{"moduleName":[],"name":"string"}}},{"range":[84,87,84,89],"value":{"type":"operator","operator":"++"}},{"range":[84,90,84,142],"value":{"type":"literal","literal":" try re-running the @dillonkearns/elm-graphql CLI "}}]}}}}]}}}],"expression":{"range":[49,22,49,28],"value":{"type":"functionOrValue","functionOrValue":{"moduleName":[],"name":"string"}}}}}}}}}}}]}}}}}}},{"range":[90,1,124,20],"value":{"type":"function","function":{"documentation":null,"signature":{"range":[90,1,90,43],"value":{"name":{"range":[90,1,90,9],"value":"toString"},"typeAnnotation":{"range":[90,12,90,43],"value":{"type":"function","function":{"left":{"range":[90,12,90,33],"value":{"type":"typed","typed":{"moduleNameAndName":{"range":[90,12,90,33],"value":{"moduleName":[],"name":"Patient_update_column"}},"args":[]}}},"right":{"range":[90,37,90,43],"value":{"type":"typed","typed":{"moduleNameAndName":{"range":[90,37,90,43],"value":{"moduleName":[],"name":"String"}},"args":[]}}}}}}}},"declaration":{"range":[91,1,124,20],"value":{"name":{"range":[91,1,91,9],"value":"toString"},"arguments":[{"range":[91,10,91,14],"value":{"type":"var","var":{"value":"enum"}}}],"expression":{"range":[92,5,124,20],"value":{"type":"case","case":{"cases":[{"pattern":{"range":[93,9,93,20],"value":{"type":"named","named":{"qualified":{"moduleName":[],"name":"Code_postal"},"patterns":[]}}},"expression":{"range":[94,13,94,26],"value":{"type":"literal","literal":"code_postal"}}},{"pattern":{"range":[96,9,96,26],"value":{"type":"named","named":{"qualified":{"moduleName":[],"name":"Date_de_naissance"},"patterns":[]}}},"expression":{"range":[97,13,97,32],"value":{"type":"literal","literal":"date_de_naissance"}}},{"pattern":{"range":[99,9,99,14],"value":{"type":"named","named":{"qualified":{"moduleName":[],"name":"Genre"},"patterns":[]}}},"expression":{"range":[100,13,100,20],"value":{"type":"literal","literal":"genre"}}},{"pattern":{"range":[102,9,102,19],"value":{"type":"named","named":{"qualified":{"moduleName":[],"name":"Id_patient"},"patterns":[]}}},"expression":{"range":[103,13,103,25],"value":{"type":"literal","literal":"id_patient"}}},{"pattern":{"range":[105,9,105,28],"value":{"type":"named","named":{"qualified":{"moduleName":[],"name":"Moyen_de_decouverte"},"patterns":[]}}},"expression":{"range":[106,13,106,34],"value":{"type":"literal","literal":"moyen_de_decouverte"}}},{"pattern":{"range":[108,9,108,12],"value":{"type":"named","named":{"qualified":{"moduleName":[],"name":"Nom"},"patterns":[]}}},"expression":{"range":[109,13,109,18],"value":{"type":"literal","literal":"nom"}}},{"pattern":{"range":[111,9,111,19],"value":{"type":"named","named":{"qualified":{"moduleName":[],"name":"Numero_rue"},"patterns":[]}}},"expression":{"range":[112,13,112,25],"value":{"type":"literal","literal":"numero_rue"}}},{"pattern":{"range":[114,9,114,13],"value":{"type":"named","named":{"qualified":{"moduleName":[],"name":"Pays"},"patterns":[]}}},"expression":{"range":[115,13,115,19],"value":{"type":"literal","literal":"pays"}}},{"pattern":{"range":[117,9,117,15],"value":{"type":"named","named":{"qualified":{"moduleName":[],"name":"Prenom"},"patterns":[]}}},"expression":{"range":[118,13,118,21],"value":{"type":"literal","literal":"prenom"}}},{"pattern":{"range":[120,9,120,12],"value":{"type":"named","named":{"qualified":{"moduleName":[],"name":"Rue"},"patterns":[]}}},"expression":{"range":[121,13,121,18],"value":{"type":"literal","literal":"rue"}}},{"pattern":{"range":[123,9,123,14],"value":{"type":"named","named":{"qualified":{"moduleName":[],"name":"Ville"},"patterns":[]}}},"expression":{"range":[124,13,124,20],"value":{"type":"literal","literal":"ville"}}}],"expression":{"range":[92,10,92,14],"value":{"type":"functionOrValue","functionOrValue":{"moduleName":[],"name":"enum"}}}}}}}}}}},{"range":[138,1,175,20],"value":{"type":"function","function":{"documentation":null,"signature":{"range":[138,1,138,51],"value":{"name":{"range":[138,1,138,11],"value":"fromString"},"typeAnnotation":{"range":[138,14,138,51],"value":{"type":"function","function":{"left":{"range":[138,14,138,20],"value":{"type":"typed","typed":{"moduleNameAndName":{"range":[138,14,138,20],"value":{"moduleName":[],"name":"String"}},"args":[]}}},"right":{"range":[138,24,138,51],"value":{"type":"typed","typed":{"moduleNameAndName":{"range":[138,24,138,29],"value":{"moduleName":[],"name":"Maybe"}},"args":[{"range":[138,30,138,51],"value":{"type":"typed","typed":{"moduleNameAndName":{"range":[138,30,138,51],"value":{"moduleName":[],"name":"Patient_update_column"}},"args":[]}}}]}}}}}}}},"declaration":{"range":[139,1,175,20],"value":{"name":{"range":[139,1,139,11],"value":"fromString"},"arguments":[{"range":[139,12,139,22],"value":{"type":"var","var":{"value":"enumString"}}}],"expression":{"range":[140,5,175,20],"value":{"type":"case","case":{"cases":[{"pattern":{"range":[141,9,141,22],"value":{"type":"string","string":{"value":"code_postal"}}},"expression":{"range":[142,13,142,29],"value":{"type":"application","application":[{"range":[142,13,142,17],"value":{"type":"functionOrValue","functionOrValue":{"moduleName":[],"name":"Just"}}},{"range":[142,18,142,29],"value":{"type":"functionOrValue","functionOrValue":{"moduleName":[],"name":"Code_postal"}}}]}}},{"pattern":{"range":[144,9,144,28],"value":{"type":"string","string":{"value":"date_de_naissance"}}},"expression":{"range":[145,13,145,35],"value":{"type":"application","application":[{"range":[145,13,145,17],"value":{"type":"functionOrValue","functionOrValue":{"moduleName":[],"name":"Just"}}},{"range":[145,18,145,35],"value":{"type":"functionOrValue","functionOrValue":{"moduleName":[],"name":"Date_de_naissance"}}}]}}},{"pattern":{"range":[147,9,147,16],"value":{"type":"string","string":{"value":"genre"}}},"expression":{"range":[148,13,148,23],"value":{"type":"application","application":[{"range":[148,13,148,17],"value":{"type":"functionOrValue","functionOrValue":{"moduleName":[],"name":"Just"}}},{"range":[148,18,148,23],"value":{"type":"functionOrValue","functionOrValue":{"moduleName":[],"name":"Genre"}}}]}}},{"pattern":{"range":[150,9,150,21],"value":{"type":"string","string":{"value":"id_patient"}}},"expression":{"range":[151,13,151,28],"value":{"type":"application","application":[{"range":[151,13,151,17],"value":{"type":"functionOrValue","functionOrValue":{"moduleName":[],"name":"Just"}}},{"range":[151,18,151,28],"value":{"type":"functionOrValue","functionOrValue":{"moduleName":[],"name":"Id_patient"}}}]}}},{"pattern":{"range":[153,9,153,30],"value":{"type":"string","string":{"value":"moyen_de_decouverte"}}},"expression":{"range":[154,13,154,37],"value":{"type":"application","application":[{"range":[154,13,154,17],"value":{"type":"functionOrValue","functionOrValue":{"moduleName":[],"name":"Just"}}},{"range":[154,18,154,37],"value":{"type":"functionOrValue","functionOrValue":{"moduleName":[],"name":"Moyen_de_decouverte"}}}]}}},{"pattern":{"range":[156,9,156,14],"value":{"type":"string","string":{"value":"nom"}}},"expression":{"range":[157,13,157,21],"value":{"type":"application","application":[{"range":[157,13,157,17],"value":{"type":"functionOrValue","functionOrValue":{"moduleName":[],"name":"Just"}}},{"range":[157,18,157,21],"value":{"type":"functionOrValue","functionOrValue":{"moduleName":[],"name":"Nom"}}}]}}},{"pattern":{"range":[159,9,159,21],"value":{"type":"string","string":{"value":"numero_rue"}}},"expression":{"range":[160,13,160,28],"value":{"type":"application","application":[{"range":[160,13,160,17],"value":{"type":"functionOrValue","functionOrValue":{"moduleName":[],"name":"Just"}}},{"range":[160,18,160,28],"value":{"type":"functionOrValue","functionOrValue":{"moduleName":[],"name":"Numero_rue"}}}]}}},{"pattern":{"range":[162,9,162,15],"value":{"type":"string","string":{"value":"pays"}}},"expression":{"range":[163,13,163,22],"value":{"type":"application","application":[{"range":[163,13,163,17],"value":{"type":"functionOrValue","functionOrValue":{"moduleName":[],"name":"Just"}}},{"range":[163,18,163,22],"value":{"type":"functionOrValue","functionOrValue":{"moduleName":[],"name":"Pays"}}}]}}},{"pattern":{"range":[165,9,165,17],"value":{"type":"string","string":{"value":"prenom"}}},"expression":{"range":[166,13,166,24],"value":{"type":"application","application":[{"range":[166,13,166,17],"value":{"type":"functionOrValue","functionOrValue":{"moduleName":[],"name":"Just"}}},{"range":[166,18,166,24],"value":{"type":"functionOrValue","functionOrValue":{"moduleName":[],"name":"Prenom"}}}]}}},{"pattern":{"range":[168,9,168,14],"value":{"type":"string","string":{"value":"rue"}}},"expression":{"range":[169,13,169,21],"value":{"type":"application","application":[{"range":[169,13,169,17],"value":{"type":"functionOrValue","functionOrValue":{"moduleName":[],"name":"Just"}}},{"range":[169,18,169,21],"value":{"type":"functionOrValue","functionOrValue":{"moduleName":[],"name":"Rue"}}}]}}},{"pattern":{"range":[171,9,171,16],"value":{"type":"string","string":{"value":"ville"}}},"expression":{"range":[172,13,172,23],"value":{"type":"application","application":[{"range":[172,13,172,17],"value":{"type":"functionOrValue","functionOrValue":{"moduleName":[],"name":"Just"}}},{"range":[172,18,172,23],"value":{"type":"functionOrValue","functionOrValue":{"moduleName":[],"name":"Ville"}}}]}}},{"pattern":{"range":[174,9,174,10],"value":{"type":"all","all":{}}},"expression":{"range":[175,13,175,20],"value":{"type":"functionOrValue","functionOrValue":{"moduleName":[],"name":"Nothing"}}}}],"expression":{"range":[140,10,140,20],"value":{"type":"functionOrValue","functionOrValue":{"moduleName":[],"name":"enumString"}}}}}}}}}}}],"comments":[{"range":[127,1,137,3],"value":"{-| Convert from a String representation to an elm representation enum.\nThis is the inverse of the Enum `toString` function. So you can call `toString` and then convert back `fromString` safely.\n\n    Swapi.Enum.Episode.NewHope\n        |> Swapi.Enum.Episode.toString\n        |> Swapi.Enum.Episode.fromString\n        == Just NewHope\n\nThis can be useful for generating Strings to use for <select> menus to check which item was selected.\n\n-}"},{"range":[88,1,89,3],"value":"{-| Convert from the union type representating the Enum to a string that the GraphQL server will recognize.\n-}"},{"range":[10,1,24,3],"value":"{-| update columns of table \"Patient\"\n\n  - Code\\_postal - column name\n  - Date\\_de\\_naissance - column name\n  - Genre - column name\n  - Id\\_patient - column name\n  - Moyen\\_de\\_decouverte - column name\n  - Nom - column name\n  - Numero\\_rue - column name\n  - Pays - column name\n  - Prenom - column name\n  - Rue - column name\n  - Ville - column name\n\n-}"},{"range":[2,1,2,47],"value":"-- https://github.com/dillonkearns/elm-graphql"},{"range":[1,1,1,85],"value":"-- Do not manually edit this file, it was auto-generated by dillonkearns/elm-graphql"}]}